logfire_mcp/__init__.py
logfire_mcp/__main__.py
logfire_mcp/main.py
iflow_mcp_logfire_mcp-0.6.2.dist-info/METADATA
iflow_mcp_logfire_mcp-0.6.2.dist-info/WHEEL
iflow_mcp_logfire_mcp-0.6.2.dist-info/entry_points.txt
iflow_mcp_logfire_mcp-0.6.2.dist-info/licenses/LICENSE
iflow_mcp_logfire_mcp-0.6.2.dist-info/RECORD
