Metadata-Version: 2.4
Name: iflow-mcp_logfire-mcp
Version: 0.6.2
Summary: The Pydantic Logfire MCP server! 🔍
Project-URL: Homepage, https://github.com/pydantic/logfire-mcp
Project-URL: Repository, https://github.com/pydantic/logfire-mcp
Project-URL: Issues, https://github.com/pydantic/logfire-mcp/issues
Author-email: Marcelo Trylesinski <marcelotryle@gmail.com>, Samuel Colvin <samuel@pydantic.dev>
License-Expression: MIT
License-File: LICENSE
Classifier: Development Status :: 4 - Beta
Classifier: Intended Audience :: Developers
Classifier: Programming Language :: Python :: 3
Classifier: Programming Language :: Python :: 3.11
Classifier: Programming Language :: Python :: 3.12
Classifier: Programming Language :: Python :: 3.13
Requires-Python: >=3.11
Requires-Dist: logfire>=3.7.1
Requires-Dist: mcp[cli]>=1.10.0
Requires-Dist: python-dotenv>=1.1.1
